[
        {
            "namakab": "[3511] BONDOWOSO",
            "version": "1",
            "kdprov": "35",
            "kdprovkab": "3511"
        },
        {
            "namakab": "[3578] KOTA SURABAYA",
            "version": "1",
            "kdprov": "35",
            "kdprovkab": "3578"
        },
        {
            "namakab": "[3519] MADIUN",
            "version": "1",
            "kdprov": "35",
            "kdprovkab": "3519"
        },
        {
            "namakab": "[3573] KOTA MALANG",
            "version": "1",
            "kdprov": "35",
            "kdprovkab": "3573"
        },
        {
            "namakab": "[3575] KOTA PASURUAN",
            "version": "1",
            "kdprov": "35",
            "kdprovkab": "3575"
        },
        {
            "namakab": "[3506] KEDIRI",
            "version": "1",
            "kdprov": "35",
            "kdprovkab": "3506"
        },
        {
            "namakab": "[3513] PROBOLINGGO",
            "version": "1",
            "kdprov": "35",
            "kdprovkab": "3513"
        },
        {
            "namakab": "[3518] NGANJUK",
            "version": "1",
            "kdprov": "35",
            "kdprovkab": "3518"
        },
        {
            "namakab": "[3574] KOTA PROBOLINGGO",
            "version": "1",
            "kdprov": "35",
            "kdprovkab": "3574"
        },
        {
            "namakab": "[3520] MAGETAN",
            "version": "1",
            "kdprov": "35",
            "kdprovkab": "3520"
        },
        {
            "namakab": "[3571] KOTA KEDIRI",
            "version": "1",
            "kdprov": "35",
            "kdprovkab": "3571"
        },
        {
            "namakab": "[3572] KOTA BLITAR",
            "version": "1",
            "kdprov": "35",
            "kdprovkab": "3572"
        },
        {
            "namakab": "[3505] BLITAR",
            "version": "1",
            "kdprov": "35",
            "kdprovkab": "3505"
        },
        {
            "namakab": "[3503] TRENGGALEK",
            "version": "1",
            "kdprov": "35",
            "kdprovkab": "3503"
        },
        {
            "namakab": "[3514] PASURUAN",
            "version": "1",
            "kdprov": "35",
            "kdprovkab": "3514"
        },
        {
            "namakab": "[3526] BANGKALAN",
            "version": "1",
            "kdprov": "35",
            "kdprovkab": "3526"
        },
        {
            "namakab": "[3504] TULUNGAGUNG",
            "version": "1",
            "kdprov": "35",
            "kdprovkab": "3504"
        },
        {
            "namakab": "[3522] BOJONEGORO",
            "version": "1",
            "kdprov": "35",
            "kdprovkab": "3522"
        },
        {
            "namakab": "[3501] PACITAN",
            "version": "1",
            "kdprov": "35",
            "kdprovkab": "3501"
        },
        {
            "namakab": "[3507] MALANG",
            "version": "1",
            "kdprov": "35",
            "kdprovkab": "3507"
        },
        {
            "namakab": "[3516] MOJOKERTO",
            "version": "1",
            "kdprov": "35",
            "kdprovkab": "3516"
        },
        {
            "namakab": "[3577] KOTA MADIUN",
            "version": "1",
            "kdprov": "35",
            "kdprovkab": "3577"
        },
        {
            "namakab": "[3517] JOMBANG",
            "version": "1",
            "kdprov": "35",
            "kdprovkab": "3517"
        },
        {
            "namakab": "[3524] LAMONGAN",
            "version": "1",
            "kdprov": "35",
            "kdprovkab": "3524"
        },
        {
            "namakab": "[3525] GRESIK",
            "version": "1",
            "kdprov": "35",
            "kdprovkab": "3525"
        },
        {
            "namakab": "[3579] KOTA BATU",
            "version": "1",
            "kdprov": "35",
            "kdprovkab": "3579"
        },
        {
            "namakab": "[3521] NGAWI",
            "version": "1",
            "kdprov": "35",
            "kdprovkab": "3521"
        },
        {
            "namakab": "[3528] PAMEKASAN",
            "version": "1",
            "kdprov": "35",
            "kdprovkab": "3528"
        },
        {
            "namakab": "[3502] PONOROGO",
            "version": "1",
            "kdprov": "35",
            "kdprovkab": "3502"
        },
        {
            "namakab": "[3529] SUMENEP",
            "version": "1",
            "kdprov": "35",
            "kdprovkab": "3529"
        },
        {
            "namakab": "[3510] BANYUWANGI",
            "version": "1",
            "kdprov": "35",
            "kdprovkab": "3510"
        },
        {
            "namakab": "[3515] SIDOARJO",
            "version": "1",
            "kdprov": "35",
            "kdprovkab": "3515"
        },
        {
            "namakab": "[3527] SAMPANG",
            "version": "1",
            "kdprov": "35",
            "kdprovkab": "3527"
        },
        {
            "namakab": "[3509] JEMBER",
            "version": "1",
            "kdprov": "35",
            "kdprovkab": "3509"
        },
        {
            "namakab": "[3523] TUBAN",
            "version": "1",
            "kdprov": "35",
            "kdprovkab": "3523"
        },
        {
            "namakab": "[3576] KOTA MOJOKERTO",
            "version": "1",
            "kdprov": "35",
            "kdprovkab": "3576"
        },
        {
            "namakab": "[3508] LUMAJANG",
            "version": "1",
            "kdprov": "35",
            "kdprovkab": "3508"
        },
        {
            "namakab": "[3512] SITUBONDO",
            "version": "1",
            "kdprov": "35",
            "kdprovkab": "3512"
        }
    ]